get_datetime/__init__.py
get_datetime-0.1.0.dist-info/LICENSE
get_datetime-0.1.0.dist-info/METADATA
get_datetime-0.1.0.dist-info/WHEEL
get_datetime-0.1.0.dist-info/top_level.txt
get_datetime-0.1.0.dist-info/RECORD
