Metadata-Version: 2.1
Name: get-datetime
Version: 0.1.0
Summary: get Simple time int and str
Home-page: https://petersell.dev
Author: Johann Petersell
Author-email: contact@petersell.dev
License: UNKNOWN
Platform: UNKNOWN
Classifier: Programming Language :: Python :: 3
Classifier: License :: OSI Approved :: MIT License
Classifier: Operating System :: OS Independent
Requires-Python: >=3.5
License-File: LICENSE
